README
setup.py
proxylet/__init__.py
proxylet/relocate.py
proxylet/streams.py
proxylet.egg-info/PKG-INFO
proxylet.egg-info/SOURCES.txt
proxylet.egg-info/dependency_links.txt
proxylet.egg-info/requires.txt
proxylet.egg-info/top_level.txt