Metadata-Version: 1.0
Name: proxylet
Version: 0.1.1
Summary: Lightweight HTTP reverse proxy built on eventlet
Home-page: UNKNOWN
Author: Ryan Kelly
Author-email: ryan@rfk.id.au
License: PSF
Keywords: HTTP reverse proxy
Platform: UNKNOWN
